simple_template_toolkit/__init__.py
simple_template_toolkit/click_helper.py
simple_template_toolkit/console_helper.py
simple_template_toolkit/constants.py
simple_template_toolkit/file_utils.py
simple_template_toolkit/insert_lines.py
simple_template_toolkit/make_shell_scripts_and_aliases.py
simple_template_toolkit/make_substitutions.py
simple_template_toolkit/manager.py
simple_template_toolkit-0.2.0.dist-info/AUTHORS.rst
simple_template_toolkit-0.2.0.dist-info/LICENSE
simple_template_toolkit-0.2.0.dist-info/METADATA
simple_template_toolkit-0.2.0.dist-info/WHEEL
simple_template_toolkit-0.2.0.dist-info/entry_points.txt
simple_template_toolkit-0.2.0.dist-info/top_level.txt
simple_template_toolkit-0.2.0.dist-info/RECORD
