Metadata-Version: 2.1
Name: simple_template_toolkit
Version: 0.2.0
Summary: Simple templating for all your simple templating projects
Home-page: https://github.com/jai-python3/simple-template-toolkit
Author: Jaideep Sundaram
Author-email: jai.python3@gmail.com
Keywords: simple_template_toolkit
Classifier: Development Status :: 2 - Pre-Alpha
Classifier: Intended Audience :: Developers
Classifier: Natural Language :: English
Classifier: Programming Language :: Python :: 3
Classifier: Programming Language :: Python :: 3.6
Classifier: Programming Language :: Python :: 3.7
Classifier: Programming Language :: Python :: 3.8
Requires-Python: >=3.6
License-File: LICENSE
License-File: AUTHORS.rst
Requires-Dist: Click >=7.0
Requires-Dist: Rich
Requires-Dist: PyYAML
